Lab_Automation-1.1.dist-info/DESCRIPTION.rst
Lab_Automation-1.1.dist-info/METADATA
Lab_Automation-1.1.dist-info/RECORD
Lab_Automation-1.1.dist-info/WHEEL
Lab_Automation-1.1.dist-info/entry_points.txt
Lab_Automation-1.1.dist-info/metadata.json
Lab_Automation-1.1.dist-info/top_level.txt
lab/Createcourse.py
lab/__init__.py
lab/coursepage.py
lab/editor.py
lab/encrypt_pass.py
lab/instr_ta_tab.py
lab/instructor_home.py
lab/instructor_tab.py
lab/log_webmail.py
lab/login.py
lab/mainwindow.py
lab/new.py
lab/registerpage.py
lab/server automated testing.py
lab/setup.py
lab/signup.py
lab/start.py
lab/student_home.py
lab/student_tab.py
lab/test_case_generation.py
lab/topframe.py
lab/tutor_home.py
lab/tutor_tab.py
lab/untitled.py
