Metadata-Version: 2.0
Name: Lab-Automation
Version: 1.1
Summary: Lab Automation Project
Home-page: https://github.com/rakhejabhai/Assembler.git
Author: Akash Rakheja
Author-email: rakhejaforu.ar@gmail.com
License: MIT
Keywords: labs submissions
Platform: UNKNOWN
Classifier: Development Status :: 3 - Alpha
Classifier: Topic :: Software Development :: Build Tools
Classifier: License :: OSI Approved :: MIT License
Classifier: Programming Language :: Python :: 2.7
Requires-Dist: exrex
Requires-Dist: json
Requires-Dist: requests
